CHANGELOG.rst
LICENSE.txt
MANIFEST.in
README.rst
VERSION.txt
setup.cfg
setup.py
TemplateAlchemy_Jinja2.egg-info/PKG-INFO
TemplateAlchemy_Jinja2.egg-info/SOURCES.txt
TemplateAlchemy_Jinja2.egg-info/dependency_links.txt
TemplateAlchemy_Jinja2.egg-info/namespace_packages.txt
TemplateAlchemy_Jinja2.egg-info/requires.txt
TemplateAlchemy_Jinja2.egg-info/top_level.txt
TemplateAlchemy_Jinja2.egg-info/zip-safe
templatealchemy_driver/__init__.py
templatealchemy_driver/jinja2.py
templatealchemy_driver/test_jinja2.py