Metadata-Version: 1.1
Name: TemplateAlchemy-Jinja2
Version: 0.1.7
Summary: Provides the Jinja2 template rendering engine to `TemplateAlchemy`
Home-page: http://github.com/cadithealth/templatealchemy-jinja2
Author: Philip J Grabner, Cadit Health Inc
Author-email: oss@cadit.com
License: MIT (http://opensource.org/licenses/MIT)
Keywords: templatealchemy jinja2 driver
Platform: UNKNOWN
Classifier: Development Status :: 4 - Beta
Classifier: Intended Audience :: Developers
Classifier: Programming Language :: Python
Classifier: Operating System :: OS Independent
Classifier: Topic :: Software Development
Classifier: Natural Language :: English
Classifier: License :: OSI Approved :: MIT License
Classifier: License :: Public Domain
